Metadata-Version: 2.4
Name: image_processing_felipeluiz93teste
Version: 0.0.4
Summary: image Processing Package using skimage
Home-page: https://github.com/FelipeLuiz93/image-processing-package.git
Author: Felipe
Requires-Python: >=3.5
Requires-Dist: matplotlib
Requires-Dist: numpy
Requires-Dist: scikit-image>=0.16.1
Dynamic: author
Dynamic: description
Dynamic: description-content-type
Dynamic: home-page
Dynamic: requires-dist
Dynamic: requires-python
Dynamic: summary
